DarkOpt/__init__.py
DarkOpt/core/_QET.py
DarkOpt/core/_TES.py
DarkOpt/core/__init__.py
DarkOpt/core/_absorber.py
DarkOpt/core/_detector.py
DarkOpt/materials/_MaterialProperties.py
DarkOpt/materials/__init__.py
DarkOpt/optimize/__init__.py
DarkOpt/optimize/_optimize.py
DarkOpt/plotting/__init__.py
DarkOpt/plotting/_plotting.py
DarkOpt/utils/__init__.py
DarkOpt/utils/_utils.py
DarkOpt-0.1.0.dist-info/METADATA
DarkOpt-0.1.0.dist-info/WHEEL
DarkOpt-0.1.0.dist-info/top_level.txt
DarkOpt-0.1.0.dist-info/RECORD
