Metadata-Version: 2.1
Name: DarkOpt
Version: 0.1.0
Summary: TES/QET based Detector modeling and optimization
Home-page: https://github.com/ucbpylegroup/DarkOpt
Author: Caleb Fink
Author-email: cwfink@berkeley.edu
License: UNKNOWN
Platform: UNKNOWN
Requires-Dist: numpy
Requires-Dist: scipy
Requires-Dist: matplotlib
